setup.cfg
setup.py
bingapi/__init__.py
bingapi/bingapi.py
bingapi/bossapi.py
bingapi.egg-info/PKG-INFO
bingapi.egg-info/SOURCES.txt
bingapi.egg-info/dependency_links.txt
bingapi.egg-info/top_level.txt