Metadata-Version: 1.0
Name: bingapi
Version: 0.02
Summary: Python Wrapper over Bing API
Home-page: https://svn.uswaretech.com/bingapi/
Author: Lakshman Prasad, Shabda Raaj
Author-email: lakshman@uswaretech.com
License: UNKNOWN
Platform: UNKNOWN
